sauronmouse.py
sauronmouse-0.0.1.dist-info/WHEEL
sauronmouse-0.0.1.dist-info/METADATA
sauronmouse-0.0.1.dist-info/RECORD
