Metadata-Version: 2.1
Name: sauronmouse
Version: 0.0.1
Summary: sauronmouse - control your mouse with your eyes
Home-page: https://github.com/ollipal/sauronmouse
License: UNKNOWN
Author: Olli Paloviita
Author-email: olli.paloviita@gmail.com
